visorRobot/__init__.py
visorRobot/visor.py
visorRobot09-0.0.1.dist-info/METADATA
visorRobot09-0.0.1.dist-info/WHEEL
visorRobot09-0.0.1.dist-info/top_level.txt
visorRobot09-0.0.1.dist-info/RECORD
